streamlit_chat_input_fileupload/__init__.py
streamlit_chat_input_fileupload/config.py
streamlit_chat_input_fileupload/chat_input_with_upload/__init__.py
streamlit_chat_input_fileupload-0.6.17.dist-info/licenses/LICENSE
streamlit_chat_input_fileupload-0.6.17.dist-info/METADATA
streamlit_chat_input_fileupload-0.6.17.dist-info/WHEEL
streamlit_chat_input_fileupload-0.6.17.dist-info/top_level.txt
streamlit_chat_input_fileupload-0.6.17.dist-info/RECORD
