Metadata-Version: 2.4
Name: streamlit-chat-input-fileupload
Version: 0.6.17
Summary: Streamlit custom component that offers chat input box for messages - with files upload widget
Author-email: Stellars Henson <konrad.jelen@gmail.com>
License-Expression: MIT
Classifier: Programming Language :: Python :: 3
Requires-Python: ~=3.12.0
License-File: LICENSE
Requires-Dist: boto3
Requires-Dist: python-dotenv
Requires-Dist: streamlit
Provides-Extra: dev
Requires-Dist: build; extra == "dev"
Requires-Dist: ipykernel; extra == "dev"
Requires-Dist: ipython; extra == "dev"
Requires-Dist: nbdime; extra == "dev"
Requires-Dist: pip; extra == "dev"
Requires-Dist: pytest; extra == "dev"
Requires-Dist: pytest-cov; extra == "dev"
Requires-Dist: toml; extra == "dev"
Requires-Dist: ruff; extra == "dev"
Requires-Dist: twine; extra == "dev"
Dynamic: license-file
